{
  "botToken": "e16230898a48dacdf280a91c5803547ac05a866158bbd282455bfdabe89ff73a834a96a8fc9121bccd56dea16d1626a8",
  "encryptionByPinCode": false,
  "botTokenEncrypted": true,
  "deleteMessagesFromTelegram": false,
  "allowedChats": [
    "scala_java"
  ],
  "mainDeviceId": "",
  "pluginVersion": "4.0.0",
  "telegramSessionType": "bot",
  "telegramSessionId": 20250831015241216,
  "betaVersion": "",
  "connectionStatusIndicatorType": "CONSTANT",
  "cacheCleanupAtStartup": false,
  "messageDistributionRules": [
    {
      "messageFilterQuery": "{{all}}",
      "messageFilterConditions": [
        {
          "conditionType": "all",
          "operation": "",
          "value": ""
        }
      ],
      "templateFilePath": "",
      "notePathTemplate": "Telegram/{{content:30}} - {{messageTime:YYYYMMDDHHmmssSSS}}.md",
      "filePathTemplate": "Telegram/{{file:type}}s/{{file:name}} - {{messageTime:YYYYMMDDHHmmssSSS}}.{{file:extension}}",
      "reversedOrder": true,
      "heading": ""
    }
  ],
  "defaultMessageDelimiter": true,
  "parallelMessageProcessing": false,
  "processOldMessages": false,
  "processOldMessagesSettings": {
    "lastProcessingDate": 1756587169,
    "daysLimit": 14,
    "dialogsLimit": 100,
    "messagesLimit": 1000,
    "chatsForSearch": []
  },
  "processOtherBotsMessages": false,
  "retryFailedMessagesProcessing": false,
  "topicNames": []
}